nubia_score/__init__.py
nubia_score/nubia.py
nubia_score/pretrained/roBERTa_MNLI/NOTE
nubia_score/pretrained/roBERTa_MNLI/dict.txt
nubia_score/pretrained/roBERTa_MNLI/mnli_label_dict.txt
nubia_score/pretrained/roBERTa_STS/input0/dict.txt
nubia_score/pretrained/roBERTa_STS/input0/test.bin
nubia_score/pretrained/roBERTa_STS/input0/test.idx
nubia_score/pretrained/roBERTa_STS/input0/train.bin
nubia_score/pretrained/roBERTa_STS/input0/train.idx
nubia_score/pretrained/roBERTa_STS/input0/valid.bin
nubia_score/pretrained/roBERTa_STS/input0/valid.idx
nubia_score/pretrained/roBERTa_STS/input1/dict.txt
nubia_score/pretrained/roBERTa_STS/input1/test.bin
nubia_score/pretrained/roBERTa_STS/input1/test.idx
nubia_score/pretrained/roBERTa_STS/input1/train.bin
nubia_score/pretrained/roBERTa_STS/input1/train.idx
nubia_score/pretrained/roBERTa_STS/input1/valid.bin
nubia_score/pretrained/roBERTa_STS/input1/valid.idx
nubia_score/pretrained/roBERTa_STS/label/train.label
nubia_score/pretrained/roBERTa_STS/label/valid.label
nubia_score-0.1.5.dist-info/LICENSE
nubia_score-0.1.5.dist-info/METADATA
nubia_score-0.1.5.dist-info/WHEEL
nubia_score-0.1.5.dist-info/top_level.txt
nubia_score-0.1.5.dist-info/RECORD
